easyreflectometry/__init__.py
easyreflectometry/__version__.py
easyreflectometry/fitting.py
easyreflectometry/main.py
easyreflectometry/plot.py
easyreflectometry/project.py
easyreflectometry/utils.py
easyreflectometry/calculators/__init__.py
easyreflectometry/calculators/calculator_base.py
easyreflectometry/calculators/factory.py
easyreflectometry/calculators/wrapper_base.py
easyreflectometry/calculators/bornagain/calculator.py
easyreflectometry/calculators/bornagain/wrapper.py
easyreflectometry/calculators/refl1d/calculator.py
easyreflectometry/calculators/refl1d/wrapper.py
easyreflectometry/calculators/refnx/calculator.py
easyreflectometry/calculators/refnx/wrapper.py
easyreflectometry/data/__init__.py
easyreflectometry/data/data_store.py
easyreflectometry/data/measurement.py
easyreflectometry/model/__init__.py
easyreflectometry/model/model.py
easyreflectometry/model/model_collection.py
easyreflectometry/model/resolution_functions.py
easyreflectometry/sample/__init__.py
easyreflectometry/sample/base_core.py
easyreflectometry/sample/assemblies/base_assembly.py
easyreflectometry/sample/assemblies/gradient_layer.py
easyreflectometry/sample/assemblies/multilayer.py
easyreflectometry/sample/assemblies/repeating_multilayer.py
easyreflectometry/sample/assemblies/surfactant_layer.py
easyreflectometry/sample/collections/base_collection.py
easyreflectometry/sample/collections/layer_collection.py
easyreflectometry/sample/collections/material_collection.py
easyreflectometry/sample/collections/sample.py
easyreflectometry/sample/elements/layers/layer.py
easyreflectometry/sample/elements/layers/layer_area_per_molecule.py
easyreflectometry/sample/elements/materials/material.py
easyreflectometry/sample/elements/materials/material_density.py
easyreflectometry/sample/elements/materials/material_mixture.py
easyreflectometry/sample/elements/materials/material_solvated.py
easyreflectometry/special/calculations.py
easyreflectometry/special/parsing.py
easyreflectometry-1.4.1.dist-info/METADATA
easyreflectometry-1.4.1.dist-info/WHEEL
easyreflectometry-1.4.1.dist-info/licenses/AUTHORS.rst
easyreflectometry-1.4.1.dist-info/licenses/LICENSE
easyreflectometry-1.4.1.dist-info/RECORD
