Metadata-Version: 2.1
Name: easyreflectometry
Version: 1.4.1
Summary: A reflectometry python package built on the EasyScience framework.
Project-URL: homepage, https://docs.easyreflectometry.org
Project-URL: documentation, https://docs.easyreflectometry.org
Author: EasyScience contributors
License: BSD 3-Clause License
License-File: AUTHORS.rst
License-File: LICENSE
Classifier: Development Status :: 3 - Alpha
Classifier: License :: OSI Approved :: BSD License
Classifier: Operating System :: OS Independent
Classifier: Programming Language :: Python :: 3
Classifier: Programming Language :: Python :: 3 :: Only
Classifier: Programming Language :: Python :: 3.11
Classifier: Programming Language :: Python :: 3.12
Classifier: Topic :: Scientific/Engineering
Requires-Python: <3.13,>=3.11
Requires-Dist: bumps
Requires-Dist: easyscience
Requires-Dist: orsopy
Requires-Dist: refl1d>=1.0.0rc0
Requires-Dist: refnx
Requires-Dist: scipp
Requires-Dist: svglib<1.6; platform_system == 'Linux'
Requires-Dist: xhtml2pdf
Provides-Extra: dev
Requires-Dist: build; extra == 'dev'
Requires-Dist: codecov; extra == 'dev'
Requires-Dist: coverage; extra == 'dev'
Requires-Dist: coveralls; extra == 'dev'
Requires-Dist: flake8; extra == 'dev'
Requires-Dist: ipykernel; extra == 'dev'
Requires-Dist: jupyter; extra == 'dev'
Requires-Dist: jupyterlab; extra == 'dev'
Requires-Dist: plopp; extra == 'dev'
Requires-Dist: pooch; extra == 'dev'
Requires-Dist: pytest; extra == 'dev'
Requires-Dist: pytest-cov; extra == 'dev'
Requires-Dist: ruff; extra == 'dev'
Requires-Dist: toml; extra == 'dev'
Requires-Dist: yapf; extra == 'dev'
Provides-Extra: docs
Requires-Dist: myst-parser; extra == 'docs'
Requires-Dist: nbsphinx; extra == 'docs'
Requires-Dist: sphinx-autodoc-typehints; extra == 'docs'
Requires-Dist: sphinx-book-theme; extra == 'docs'
Requires-Dist: sphinx-copybutton; extra == 'docs'
Requires-Dist: sphinx==8.1.3; extra == 'docs'
Requires-Dist: toml; extra == 'docs'
